minerva/__init__.py
minerva/client.py
minerva_py-0.0.1.dist-info/LICENSE
minerva_py-0.0.1.dist-info/METADATA
minerva_py-0.0.1.dist-info/WHEEL
minerva_py-0.0.1.dist-info/top_level.txt
minerva_py-0.0.1.dist-info/RECORD
