Metadata-Version: 2.1
Name: minerva-py
Version: 0.0.1
Summary: Python client for Minerva
Home-page: https://github.com/MarkDevTeamMgt/minerva-py
Author: Lingfei Hu
Author-email: hulingfei84@gmail.com
License: Apache License, Version 2.0
Platform: UNKNOWN
Classifier: License :: OSI Approved :: Apache Software License
Classifier: Operating System :: OS Independent
Classifier: Programming Language :: Python :: 3
Requires-Python: >=3.6
Requires-Dist: requests
Requires-Dist: pyjwt
